odoo8_addon_shopinvader_m2mcategories-8.0.1.0.0.99.dev6-py3.8-nspkg.pth
odoo_addons/shopinvader_m2mcategories/README.rst
odoo_addons/shopinvader_m2mcategories/__init__.py
odoo_addons/shopinvader_m2mcategories/__openerp__.py
odoo_addons/shopinvader_m2mcategories/models/__init__.py
odoo_addons/shopinvader_m2mcategories/models/product.py
odoo_addons/shopinvader_m2mcategories/tests/__init__.py
odoo_addons/shopinvader_m2mcategories/tests/test_product.py
odoo8_addon_shopinvader_m2mcategories-8.0.1.0.0.99.dev6.dist-info/METADATA
odoo8_addon_shopinvader_m2mcategories-8.0.1.0.0.99.dev6.dist-info/WHEEL
odoo8_addon_shopinvader_m2mcategories-8.0.1.0.0.99.dev6.dist-info/namespace_packages.txt
odoo8_addon_shopinvader_m2mcategories-8.0.1.0.0.99.dev6.dist-info/top_level.txt
odoo8_addon_shopinvader_m2mcategories-8.0.1.0.0.99.dev6.dist-info/RECORD
